cognee_community_graph_adapter_memgraph/__init__.py
cognee_community_graph_adapter_memgraph/memgraph_adapter.py
cognee_community_graph_adapter_memgraph-0.0.2.dist-info/METADATA
cognee_community_graph_adapter_memgraph-0.0.2.dist-info/WHEEL
cognee_community_graph_adapter_memgraph-0.0.2.dist-info/RECORD
