Metadata-Version: 2.4
Name: cognee-community-graph-adapter-memgraph
Version: 0.0.2
Summary: Memgraph graph database adapter for cognee
Project-URL: Homepage, https://github.com/topoteretes/cognee
Project-URL: Repository, https://github.com/topoteretes/cognee-community
Author-email: Cognee Team <hello@cognee.ai>
Requires-Python: <=3.13,>=3.10
Requires-Dist: cognee[neo4j]>=0.2.1
